{
  "productId": "ext-1190294015",
  "slug": "meditopia",
  "name": "Meditopia",
  "domain": "медитация / сон / mindfulness / ментальное здоровье",
  "oneLiner": "мультиязычное приложение для медитации, сна и тревоги, freemium-подписка, iOS+Android. Сильно представлено за пределами США (Турция, Европа, Латинская Америка)",
  "pricing": "freemium: ограниченный бесплатный контент, подписка Premium (помесячно/год), часто промо-цены и пробный период",
  "keyFeatures": [
    "guided meditations",
    "sleep stories and sleep sounds",
    "breathing exercises",
    "mood / emotion tracking",
    "anxiety and stress programs",
    "multilingual content (не только английский)",
    "daily quotes / motivation",
    "music and ambient sounds"
  ],
  "competitors": ["Calm", "Headspace", "Insight Timer", "Balance", "Breethe"],
  "goodObservationExamples": [
    {
      "rating": 1,
      "trigger": "the free trial charged me immediately for the whole year",
      "observation": "Кнопка бесплатного пробного периода сразу списывает полную годовую подписку — пробного доступа фактически нет",
      "specificity": "high"
    },
    {
      "rating": 2,
      "trigger": "the sleep meditation cuts off in the middle of the night",
      "observation": "Длинная сонная медитация обрывается среди ночи и будит — непрерывность аудио в sleep-сценарии ломается",
      "specificity": "high"
    },
    {
      "rating": 3,
      "trigger": "I use it in Turkish and half the content is only in English",
      "observation": "Часть контента доступна только на английском — мультиязычные пользователи платят, но получают урезанный каталог на родном языке",
      "specificity": "high"
    }
  ],
  "badObservationExamples": [
    "App is great, love it (praise, no mechanism)",
    "Too expensive (commodity billing complaint)",
    "Doesn't work (no detail)",
    "Nice voice (commodity)"
  ]
}
