{
  "groups": [
    {
      "id": "bany-cenzura-i-slezhka",
      "name": "Баны без апелляции, теневая цензура и слежка",
      "insight_ids": [
        "arbitrary-account-deletion-no-appeal",
        "new-accounts-banned-fast",
        "shadowban-lgbtq-content",
        "taiwan-flag-hidden-china-policy",
        "device-lock-blocks-new-accounts",
        "excessive-personal-data-collection",
        "age-rating-contradicts-signup",
        "block-feature-ineffective"
      ]
    },
    {
      "id": "platno-za-rodnoy-yazyk",
      "name": "Плати за родной язык: подписка на базовое",
      "insight_ids": [
        "core-language-settings-behind-paywall",
        "basic-social-features-paywalled",
        "translate-locked-after-free-limit",
        "message-quota-before-payment",
        "language-limit-three",
        "location-on-profile-no-hide",
        "phone-verification-forced"
      ]
    },
    {
      "id": "trial-lovushki-i-apseyl",
      "name": "Триал-ловушки, реклама поверх оплаты и навязчивый VIP",
      "insight_ids": [
        "trial-button-charges-full-year",
        "vip-features-stripped-into-paid-addons",
        "forced-purchase-no-trial",
        "trial-cancel-still-charges-blocks-store",
        "trial-excludes-chinese-users",
        "ads-shown-to-paying-users",
        "ads-injected-on-home-and-switching",
        "scammy-cluttered-interface",
        "manipulative-bot-notifications"
      ]
    },
    {
      "id": "perepiska-teryaetsya",
      "name": "Сообщения не доходят, переписка теряется",
      "insight_ids": [
        "messages-not-delivered",
        "no-cross-device-sync",
        "deleting-one-chat-deletes-another",
        "phantom-messages-not-saved",
        "cant-type-history-lost",
        "deleting-media-no-storage-freed",
        "chat-tap-opens-random-profile"
      ]
    },
    {
      "id": "ne-otkryvaetsya-vyletaet",
      "name": "Не открывается, вылетает, греет телефон",
      "insight_ids": [
        "app-crashes-on-open",
        "network-error-blocks-login",
        "session-drops-disconnected",
        "ipad-back-from-profile-greys-out",
        "ipad-specific-glitches",
        "performance-degrades-overheats",
        "web-version-jwt-error",
        "moments-photo-scrolls-to-top",
        "whiteboard-broken-months"
      ]
    },
    {
      "id": "golosovye-komnaty-i-mikrofon",
      "name": "Голосовые комнаты: пропадает звук, микрофон не выключается",
      "insight_ids": [
        "voice-room-audio-dies",
        "mic-stays-on-after-leaving",
        "voice-room-title-edit-broken"
      ]
    },
    {
      "id": "uchyoba-podmenena-botami-i-flirtom",
      "name": "Учёба подменена ботами, флиртом и трансляциями",
      "insight_ids": [
        "bots-instead-of-real-people",
        "ai-tutor-no-translation",
        "ai-support-template-replies",
        "correction-tool-letter-level",
        "turned-into-livestream-platform",
        "turns-into-dating-flirting",
        "no-gender-filter-floods-messages",
        "connect-tab-shows-no-partners",
        "wrong-language-shown-in-picker",
        "birthday-age-locked"
      ]
    }
  ]
}
