{"groups":[{"id":"mekhanika-skrollinga-ustalost","name":"Механика скроллинга утомляет вместо расслабления — скорость, большой палец и соревновательный азарт","insight_ids":["scroll-speed-fixed-too-fast","scroll-gesture-tiring","scroll-activates-competition","slow-pace-amplifies-anxiety","interaction-only-scroll"]},{"id":"kontentnyy-odnoobraziye","name":"Единственный пейзаж быстро надоедает — однообразие сцены подрывает расслабляющий эффект","insight_ids":["content-repetitive-single-scene","ineffective-for-acute-stress"]},{"id":"zvuk-i-ekran-v-temnote","name":"Звук и яркость экрана в тёмной комнате — неработающее аудио и слишком яркий минимум","insight_ids":["sound-silent-dnd-mode","audio-broken-persistent","screen-too-bright-min"]},{"id":"taymer-i-interfeys-otвlekayut","name":"Таймер и интерфейс мешают засыпанию — счётчик на экране, неполный уход в сон и непонятный онбординг","insight_ids":["timer-no-device-sleep","screen-numbers-distracting","onboarding-no-instructions"]}]}