{"groups":[{"id":"ezhednevnaya-praktika-i-privychka","name":"Ежедневная практика аффирмаций как привычка — в дороге, по расписанию, для осознанности","insight_ids":["commute-use-case-stress","affirmation-schedule-by-day","mindfulness-habit-formation"]},{"id":"kachestvo-golosa-i-teksta","name":"Голос и текст аффирмаций — роботизированность, опечатки и гендерные предпочтения","insight_ids":["voice-gender-preference","robotic-voice-reduces-effect","content-typos-low-quality"]},{"id":"paywall-i-ogranichennaya-besplatnaya","name":"Платный барьер до старта и скудная бесплатная версия — нельзя оценить перед оплатой","insight_ids":["paywall-before-trial","free-version-too-limited"]},{"id":"tekhnicheskiye-sboi-registratsiya","name":"Технические сбои при регистрации и воспроизведении — зависания, молчащий звук, несохраняющиеся записи","insight_ids":["no-audio-after-registration","registration-freeze","custom-voice-recording-not-saved"]},{"id":"widget-i-podderzhka","name":"Виджет и поддержка разработчика — ограничения экрана и оперативный личный отклик","insight_ids":["widget-no-list-selection","responsive-developer-support"]}]}