{
  "groups": [
    {
      "id": "spam-paywall-v-rodah",
      "name": "Реклама и оплата лезут прямо в роды",
      "insight_ids": [
        "review-prompts-interrupt",
        "promo-notifications-other-apps",
        "paywall-mid-labor",
        "free-record-limit"
      ]
    },
    {
      "id": "podvodit-v-glavnyy-moment",
      "name": "Подводит в самый нужный момент схватки",
      "insight_ids": [
        "no-lock-screen-access",
        "timer-double-speed",
        "app-not-recording",
        "app-wont-stay-open",
        "start-button-freezes",
        "edit-keeps-counting-prev"
      ]
    },
    {
      "id": "tesnyy-ekran-i-pravki",
      "name": "Тесный экран и неудобная правка записей",
      "insight_ids": [
        "intensity-slider-unresponsive",
        "timeline-shows-limited-history",
        "no-dark-mode-night",
        "stats-hidden-in-menu",
        "graph-settings-not-saved",
        "tiny-timer-wastes-space",
        "edit-times-buggy"
      ]
    },
    {
      "id": "chasy-ne-derzhat-slova",
      "name": "Часы не держат обещанного",
      "insight_ids": [
        "watch-needs-phone",
        "watch-no-sync-to-phone",
        "watch-no-end-register"
      ]
    },
    {
      "id": "istoriya-rodov-kak-pamyat",
      "name": "История родов как память — и как её теряют",
      "insight_ids": [
        "celebrity-keepsake-history-wipe",
        "history-cap-no-export"
      ]
    },
    {
      "id": "tochnost-po-medstandartu",
      "name": "Точность отсчёта по медицинским меркам",
      "insight_ids": [
        "interval-from-end-not-start",
        "coarse-time-adjust",
        "intensity-scale-too-coarse",
        "edit-retroactively"
      ]
    }
  ]
}
