[
  {
    "slug": "day-one-daily-journal-diary",
    "productId": "cmpsyukjp20xfughv03uzsj3u",
    "appleId": 1044867788,
    "name": "Day One: Daily Journal & Diary"
  },
  {
    "slug": "shmoody-mood-habit-tracker-1534196157",
    "productId": "cmptcb96w0owaugc334upfloa",
    "appleId": 1203637303,
    "name": "Fabulous: Daily Habit Tracker"
  },
  {
    "slug": "dailybean-simplest-journal-1553223828",
    "productId": "cmq7ultdl00qjugicvvoq019t",
    "appleId": 1553223828,
    "name": "DailyBean - simplest journal"
  },
  {
    "slug": "breeze-start-self-discovery",
    "productId": "cmpsyti791yu1ughvpoka3jvt",
    "appleId": 1450365119,
    "name": "Breeze: Start Self-Discovery"
  },
  {
    "slug": "daylio-journal-mood-tracker",
    "productId": "cmpt0tjt51rspugfegqwot3nh",
    "appleId": 1194023242,
    "name": "Daylio Journal - Mood Tracker"
  },
  {
    "slug": "planner-journal-zinnia-1485310935",
    "productId": "cmq7ulsdu00qgugicbty1k1vr",
    "appleId": 1485310935,
    "name": "Planner & Journal - Zinnia"
  },
  {
    "slug": "stoic-journal-mental-health-1312926037",
    "productId": "cmq7ulv6m00qpugicq1tquxo3",
    "appleId": 1312926037,
    "name": "stoic. journal & mental health"
  },
  {
    "slug": "emmo-日记与笔记-1508326506",
    "productId": "cmq7uluau00qmugicd2fyo4oh",
    "appleId": 1508326506,
    "name": "EMMO - 日记与笔记"
  },
  {
    "slug": "how-we-feel",
    "productId": "cmpsyw1t9246jughvhv2xsu93",
    "appleId": 1562706384,
    "name": "How We Feel"
  },
  {
    "slug": "my-diary-journal-with-lock",
    "productId": "cmpt8u9v01h5uugx3k2hnds4u",
    "appleId": 1579321589,
    "name": "My Diary - Journal with Lock"
  }
]
