[
  {
    "slug": "clay-story-templates-frames",
    "productId": "cmq7uqm5804o0ugic2d5ynr8j",
    "appleId": 1469553582,
    "name": "Clay – Story Templates Frames"
  },
  {
    "slug": "contacts-address-book",
    "productId": "cmq7uqrir0500ugic5xzn8emj",
    "appleId": 579616837,
    "name": "Contacts+ | Address Book"
  },
  {
    "slug": "cloze-relationship-management",
    "productId": "cmq7uqplv04vvugiczo7n14b0",
    "appleId": 596927802,
    "name": "Cloze Relationship Management"
  },
  {
    "slug": "cardhop-contacts",
    "productId": "cmq7uqtio0506ugic1jzmfnea",
    "appleId": 1448744070,
    "name": "Cardhop Contacts"
  },
  {
    "slug": "dex-rolodex-and-personal-crm",
    "productId": "cmq7uqjy104kzugicycam1ybp",
    "appleId": 1472132715,
    "name": "Dex - Rolodex and Personal CRM"
  },
  {
    "slug": "affinity-crm",
    "productId": "cmq7uqshz0503ugicup9irclo",
    "appleId": 1241506283,
    "name": "Affinity CRM"
  }
]
